SEQ/pc_update/pc_update.v
module pc_update(
input clk,Cnd,
input [3:0]icode,
input [63:0]valP,
input [63:0]valC,
input [63:0]valM,
output reg[63:0]PC_u
);

always @(*)
begin
    
    PC_u = 64'd0;

    PC_u = valP;
    if(icode == 4'd7) // jXX
    begin
        if(Cnd == 1)
        begin
            PC_u = valC;
        end
    end
    else if(icode == 4'd8) // call
    begin
        PC_u = valC;
    end
    else if(icode == 4'd9) // ret
    begin
        PC_u = valM;
    end
end
endmodule

SEQ/pc_update/pc_update_tb.v
`include "pc_update.v"

module testbench;

reg clk,Cnd;
reg [3:0]icode;
reg [63:0]valP,valC,valM;
wire [63:0]PC_u;

pc_update call(.clk(clk), .Cnd(Cnd), .icode(icode), .valP(valP), .valC(valC), .valM(valM), .PC_u(PC_u));

initial
begin
    $dumpfile("pc_update.vcd");
    $dumpvars(0,testbench);
end

always #5 clk = ~clk;
initial
begin
    $monitor($time," clk %d; icode=%d; Cnd=%d; valP=%d; valC=%d; valM=%d; PC=%d",clk,icode,Cnd,valP,valC,valM,PC_u);
end

initial
begin
    clk = 1;
    #5 icode = 4'd7; Cnd = 0; valP = 64'd4; valC = 64'd8; valM = 64'd0;

    #10 icode = 4'd7; Cnd = 1; valP = 64'd4; valC = 64'd8; valM = 64'd0;

    #10 icode = 4'd8; Cnd = 0; valP = 64'd1; valC = 64'd2; valM = 64'd3;

    #10 icode = 4'd9; Cnd = 1; valP = 64'd3; valC = 64'd6; valM = 64'd9;

    #10 icode = 4'd3; Cnd = 0; valP = 64'd10; valC = 64'd20; valM = 64'd30;

    #10 icode = 4'd5; Cnd = 0; valP = 64'd5; valC = 64'd10; valM = 64'd15;
    #5 $finish;
end
endmodule

SEQ/pc_update/pc_update.vcd
$date
	Wed Feb 21 22:20:02 2024
$end
$version
	Icarus Verilog
$end
$timescale
	1s
$end
$scope module testbench $end
$var wire 64 ! PC_u [63:0] $end
$var reg 1 " Cnd $end
$var reg 1 # clk $end
$var reg 4 $ icode [3:0] $end
$var reg 64 % valC [63:0] $end
$var reg 64 & valM [63:0] $end
$var reg 64 ' valP [63:0] $end
$scope module call $end
$var wire 1 " Cnd $end
$var wire 1 # clk $end
$var wire 4 ( icode [3:0] $end
$var wire 64 ) valC [63:0] $end
$var wire 64 * valM [63:0] $end
$var wire 64 + valP [63:0] $end
$var reg 64 , PC_u [63:0] $end
$upscope $end
$upscope $end
$enddefinitions $end
#0
$dumpvars
b0 ,
bx +
bx *
bx )
bx (
bx '
bx &
bx %
bx $
1#
x"
b0 !
$end
#5
b100 !
b100 ,
b0 &
b0 *
b1000 %
b1000 )
b100 '
b100 +
0"
b111 $
b111 (
0#
#10
b0 !
b0 ,
1#
#15
b1000 !
b1000 ,
0#
1"
#20
b0 !
b0 ,
1#
#25
b10 !
b10 ,
0#
b11 &
b11 *
b10 %
b10 )
b1 '
b1 +
0"
b1000 $
b1000 (
#30
b0 !
b0 ,
1#
#35
b1001 !
b1001 ,
0#
b1001 &
b1001 *
b110 %
b110 )
b11 '
b11 +
1"
b1001 $
b1001 (
#40
b0 !
b0 ,
1#
#45
b1010 !
b1010 ,
0#
b11110 &
b11110 *
b10100 %
b10100 )
b1010 '
b1010 +
0"
b11 $
b11 (
#50
b0 !
b0 ,
1#
#55
b101 !
b101 ,
0#
b1111 &
b1111 *
b1010 %
b1010 )
b101 '
b101 +
b101 $
b101 (
#60
b0 !
b0 ,
1#
