SEQ/memory/memory.v
module memory(
input clk,
input [3:0]icode,
input [63:0]valA,
input [63:0]valE,
input [63:0]valP,
output reg[63:0]valM,
output reg dmem_error
);

reg [63:0]data_mem[0:1023];
reg read,write;
reg [63:0]address;
reg [63:0]data_w;

initial
begin
    data_mem[0] = 64'd0;
    data_mem[1] = 64'd1;
    data_mem[2] = 64'd2;
    data_mem[3] = 64'd3;
    data_mem[4] = 64'd4;
    data_mem[5] = 64'd5;
    data_mem[6] = 64'd6;
    data_mem[7] = 64'd7;
    data_mem[8] = 64'd8;
    data_mem[9] = 64'd9;
    data_mem[10] = 64'd10;
end

always @(negedge clk)
begin
    
    address = 64'hf;
    data_w = 64'hf;
    read = 0; write = 0;
    valM = 64'hf;
    dmem_error = 0;

    if(icode == 4'd4) // rmmovq
    begin
        data_w = valA;
        address = valE;
        write = 1;
    end
    else if(icode == 4'd5) // mrmovq
    begin
        address = valE;
        read = 1;
    end
    else if(icode == 4'd8) // call
    begin
        data_w = valP;
        address = valE;
        write = 1;
    end
    else if(icode == 4'd9) // ret
    begin
        address = valA;
        read = 1;
    end
    else if(icode == 4'd10) // pushq
    begin
        data_w = valA;
        address = valE;
        write = 1;
    end
    else if(icode == 4'd11) // popq
    begin
        address = valA;
        read = 1;
    end

        // $display($time ," address=%d, data_w=%d, valA=%d, valE=%d",address, data_w,valA,valE);

    if(address>=0 && address<1024)
    begin
        if(read == 1 && write == 0)
        begin
            valM = data_mem[address];
        end
        else if(read == 0 && write == 1)
        begin
            data_mem[address] = data_w;
        end
        else if(read == 1 && write == 1)
        begin
            dmem_error = 1;
        end
    end
    else
    begin
        dmem_error = 1;
    end

        // $display($time, "dmem_error=%d", dmem_error);

end
endmodule

SEQ/memory/memory_tb.v
`include "memory.v"

module testbench;

reg clk;
reg [3:0]icode;
reg [63:0]valA,valE,valP;
wire [63:0]valM;
wire dmem_error;

memory call(.clk(clk), .icode(icode), .valA(valA), .valE(valE), .valP(valP), .valM(valM), .dmem_error(dmem_error));

initial
begin
    $dumpfile("memory.vcd");
    $dumpvars(0,testbench);
end

always #5 clk = ~clk;
initial
begin
    $monitor($time," clk %d: icode=%d, valA=%d, valE=%d, valP=%d, valM=%d, dmem_error=%d",clk,icode,valA,valE,valP,valM,dmem_error);
end

initial
begin
    clk = 1;

    #5 icode = 4'd4; valA = 64'd100; valE = 64'd24; valP = 64'd0;

    #10 icode = 4'd5; valA = 64'd0; valE = 64'd8; valP = 64'd3;

    #10 icode = 4'd8; valA = 64'd0; valE = 64'd32; valP = 64'd64;

    #10 icode = 4'd9; valA = 64'd32; valE = 64'd0; valP = 64'd1;

    #10 icode = 4'd10; valA = 64'd10; valE = 64'd20; valP = 64'd2;

    #10 icode = 4'd11; valA = 64'd20; valE = 64'd0; valP = 64'd7;

    #10 icode = 4'd4; valA = 64'd0; valE = 64'd1200; valP = 64'd0;

    #10 icode = 4'd3; valA = 64'd1; valE = 64'd1; valP = 64'd1;
    #5 $finish;
end
endmodule

SEQ/memory/memory.vcd
$date
	Thu Feb 22 12:48:48 2024
$end
$version
	Icarus Verilog
$end
$timescale
	1s
$end
$scope module testbench $end
$var wire 64 ! valM [63:0] $end
$var wire 1 " dmem_error $end
$var reg 1 # clk $end
$var reg 4 $ icode [3:0] $end
$var reg 64 % valA [63:0] $end
$var reg 64 & valE [63:0] $end
$var reg 64 ' valP [63:0] $end
$scope module call $end
$var wire 1 # clk $end
$var wire 4 ( icode [3:0] $end
$var wire 64 ) valA [63:0] $end
$var wire 64 * valE [63:0] $end
$var wire 64 + valP [63:0] $end
$var reg 64 , address [63:0] $end
$var reg 64 - data_w [63:0] $end
$var reg 1 " dmem_error $end
$var reg 1 . read $end
$var reg 64 / valM [63:0] $end
$var reg 1 0 write $end
$upscope $end
$upscope $end
$enddefinitions $end
#0
$dumpvars
00
b1111 /
0.
b1111 -
b1111 ,
bx +
bx *
bx )
bx (
bx '
bx &
bx %
bx $
1#
0"
b1111 !
$end
#5
b0 '
b0 +
b11000 &
b11000 *
b1100100 %
b1100100 )
b100 $
b100 (
0#
#10
10
b11000 ,
b1100100 -
1#
#15
0#
b11 '
b11 +
b1000 &
b1000 *
b0 %
b0 )
b101 $
b101 (
#20
b1000 !
b1000 /
1.
b1111 -
b1000 ,
00
1#
#25
0#
b1000000 '
b1000000 +
b100000 &
b100000 *
b1000 $
b1000 (
#30
10
b1000000 -
b100000 ,
b1111 !
b1111 /
0.
1#
#35
0#
b1 '
b1 +
b0 &
b0 *
b100000 %
b100000 )
b1001 $
b1001 (
#40
b1000000 !
b1000000 /
1.
b1111 -
b100000 ,
00
1#
#45
0#
b10 '
b10 +
b10100 &
b10100 *
b1010 %
b1010 )
b1010 $
b1010 (
#50
10
b1010 -
b10100 ,
b1111 !
b1111 /
0.
1#
#55
0#
b111 '
b111 +
b0 &
b0 *
b10100 %
b10100 )
b1011 $
b1011 (
#60
b1010 !
b1010 /
1.
b1111 -
b10100 ,
00
1#
#65
0#
b0 '
b0 +
b10010110000 &
b10010110000 *
b0 %
b0 )
b100 $
b100 (
#70
1"
10
b0 -
b10010110000 ,
b1111 !
b1111 /
0.
1#
#75
0#
b1 '
b1 +
b1 &
b1 *
b1 %
b1 )
b11 $
b11 (
#80
0"
b1111 -
b1111 ,
00
1#
