SEQ/decode/decode.v
module decode(
input clk,
input [3:0]icode,
input [3:0]rA,
input [3:0]rB,
output reg[63:0]valA,
output reg[63:0]valB
);

reg [63:0]reg_mem[0:14];

initial
begin
    reg_mem[0] = 64'd0;
    reg_mem[1] = 64'd1;
    reg_mem[2] = 64'd2;
    reg_mem[3] = 64'd3;
    reg_mem[4] = 64'd32;
    reg_mem[5] = 64'd5;
    reg_mem[6] = 64'd6;
    reg_mem[7] = 64'd7;
    reg_mem[8] = 64'd8;
    reg_mem[9] = 64'd9;
    reg_mem[10] = 64'd10;
    reg_mem[11] = 64'd11;
    reg_mem[12] = 64'd12;
    reg_mem[13] = 64'd13;
    reg_mem[14] = 64'd14;
end


always @(*)
begin
    
    // valA = 64'hf;
    // valB = 64'hf;
    
    if(clk == 1)
    begin
        if(icode == 4'd2) // cmovXX
        begin
            valA = reg_mem[rA];
            valB = 0;
        end
        else if(icode == 4'd4) // rmmovq
        begin
            valA = reg_mem[rA];
            valB = reg_mem[rB];
        end
        else if(icode == 4'd5) // mrmovq
        begin
            valB = reg_mem[rB];
        end
        else if(icode == 4'd6) // OPq
        begin
            valA = reg_mem[rA];
            valB = reg_mem[rB];
        end
        else if(icode == 4'd8) // call
        begin
            valB = reg_mem[4]; 
        end
        else if(icode == 4'd9) // ret
        begin
            valA = reg_mem[4];
            valB = reg_mem[4];
        end
        else if(icode == 4'd10) // pushq
        begin
            valA = reg_mem[rA];
            valB = reg_mem[4];
        end
        else if(icode == 4'd11) // popq
        begin
            valA = reg_mem[4];
            valB = reg_mem[4];
        end
    end

end
endmodule

SEQ/decode/decode_tb.v
`include "decode.v"

module testbench;

reg clk;
reg [3:0]icode,rA,rB;
wire [63:0]valA,valB;

decode call (.clk(clk), .icode(icode), .rA(rA), .rB(rB), .valA(valA), .valB(valB));

initial
begin
    $dumpfile("decode.vcd");
    $dumpvars(0,testbench);
end

always #5 clk = ~clk;
initial
begin
    $monitor($time," clk %d: icode=%d, rA=%d, rB=%d, valA=%d, valB=%d",clk,icode,rA,rB,valA,valB);
end

initial
begin

    clk = 1;
    #5 icode = 4'd2; rA = 4'd0; rB = 4'd1;

    #10 icode = 4'd4; rA = 4'd1; rB = 4'd2;

    #10 icode = 4'd5; rA = 4'd0; rB = 4'd3;

    #10 icode = 4'd6; rA = 4'd1; rB = 4'd3;

    #10 icode = 4'd8; rA = 4'd8; rB = 4'd0;

    #10 icode = 4'd9; rA = 4'd9; rB = 4'd10;

    #10 icode = 4'd10; rA = 4'd2; rB = 4'd0;

    #10 icode = 4'd11; rA = 4'd9; rB = 4'd1;

    #10 icode = 4'd3; rA = 4'd2; rB = 4'd8;
    #5 $finish;

end
endmodule

SEQ/decode/decode.vcd
$date
	Thu Feb 22 13:28:07 2024
$end
$version
	Icarus Verilog
$end
$timescale
	1s
$end
$scope module testbench $end
$var wire 64 ! valB [63:0] $end
$var wire 64 " valA [63:0] $end
$var reg 1 # clk $end
$var reg 4 $ icode [3:0] $end
$var reg 4 % rA [3:0] $end
$var reg 4 & rB [3:0] $end
$scope module call $end
$var wire 1 # clk $end
$var wire 4 ' icode [3:0] $end
$var wire 4 ( rA [3:0] $end
$var wire 4 ) rB [3:0] $end
$var reg 64 * valA [63:0] $end
$var reg 64 + valB [63:0] $end
$upscope $end
$upscope $end
$enddefinitions $end
#0
$dumpvars
b1111 +
b1111 *
bx )
bx (
bx '
bx &
bx %
bx $
1#
b1111 "
b1111 !
$end
#5
b1 &
b1 )
b0 %
b0 (
b10 $
b10 '
0#
#10
b0 !
b0 +
b0 "
b0 *
1#
#15
b1111 !
b1111 +
b1111 "
b1111 *
0#
b10 &
b10 )
b1 %
b1 (
b100 $
b100 '
#20
b10 !
b10 +
b1 "
b1 *
1#
#25
b1111 !
b1111 +
b1111 "
b1111 *
0#
b11 &
b11 )
b0 %
b0 (
b101 $
b101 '
#30
b11 !
b11 +
1#
#35
b1111 !
b1111 +
0#
b1 %
b1 (
b110 $
b110 '
#40
b11 !
b11 +
b1 "
b1 *
1#
#45
b1111 !
b1111 +
b1111 "
b1111 *
0#
b0 &
b0 )
b1000 %
b1000 (
b1000 $
b1000 '
#50
b100000 !
b100000 +
1#
#55
b1111 !
b1111 +
0#
b1010 &
b1010 )
b1001 %
b1001 (
b1001 $
b1001 '
#60
b100000 !
b100000 +
b100000 "
b100000 *
1#
#65
b1111 !
b1111 +
b1111 "
b1111 *
0#
b0 &
b0 )
b10 %
b10 (
b1010 $
b1010 '
#70
b100000 !
b100000 +
b10 "
b10 *
1#
#75
b1111 !
b1111 +
b1111 "
b1111 *
0#
b1 &
b1 )
b1001 %
b1001 (
b1011 $
b1011 '
#80
b100000 !
b100000 +
b100000 "
b100000 *
1#
#85
b1111 !
b1111 +
b1111 "
b1111 *
0#
b1000 &
b1000 )
b10 %
b10 (
b11 $
b11 '
